pyanova/__init__.py
pyanova/pyanova.py
pyanova-0.2.0.dist-info/LICENSE
pyanova-0.2.0.dist-info/METADATA
pyanova-0.2.0.dist-info/WHEEL
pyanova-0.2.0.dist-info/top_level.txt
pyanova-0.2.0.dist-info/RECORD
