Metadata-Version: 2.1
Name: pyanova
Version: 0.2.0
Summary: A Python Library for Anova Precision Cooker
Home-page: https://github.com/c3V6a2Vy/pyanova
Author: c3V6a2Vy
Author-email: c3V6a2Vy@protonmail.com
License: Apache License 2.0
Platform: UNKNOWN
Classifier: Intended Audience :: Developers
Classifier: License :: OSI Approved :: Apache Software License
Classifier: Programming Language :: Python
Classifier: Programming Language :: Python :: 2.7
Classifier: Programming Language :: Python :: 3.4
Classifier: Programming Language :: Python :: 3.5
Classifier: Programming Language :: Python :: 3.6
Classifier: Programming Language :: Python :: 3.7
Requires-Dist: pygatt
Requires-Dist: pexpect
